{
    "tags": [
        {
            "color": "#F18281", 
            "name": "Modify"
        }, 
        {
            "color": "#20EF31", 
            "name": "Retrieve"
        }, 
        {
            "color": "#6F9AD7", 
            "name": "Pandas"
        }
    ], 
    "variations": [
        {
            "id": "fill_with_a_value_on_a_column", 
            "title": "Fill with a value on a column"
        }, 
        {
            "id": "fill_with_a_value_on_multiple_columns", 
            "title": "Fill with a value on multiple columns"
        }, 
        {
            "id": "fill_with_the_last_or_the_next_value", 
            "title": "Fill with the last or the next value"
        }, 
        {
            "id": "fill_with_a_value_based_on_an_aggregation", 
            "title": "Fill with a value based on an aggregation"
        }
    ], 
    "title": "Fill missing values",
    "category" : "py-std-3rd"
}