{
  "title": "Load a dataset",
  "variations": [
    {
      "id": "js",
      "title": "javascript"
    },
    {
      "id": "html",
      "title": "html"
    },
    {
      "id": "css",
      "title": "css"
    },
    {
      "id": "py",
      "title": "python"
    }
  ],
  "tags": [
    {
      "name": "Dataframe",
      "color": "#7f7f7f"
    }
  ],
  "isShared": true,
  "libraries": [],
  "userCreation": "admin",
  "userEdition": "admin",
  "creationDate": 1442235428117,
  "editionDate": 1442236314870
}