{
    "tags": [
        {
            "color": "#E0EEE1", 
            "name": "Partitions"
        }
    ], 
    "variations": [
        {
            "id": "partitions_write_simple", 
            "title": "Simple case"
        },
        {
            "id": "partitions_write_custom", 
            "title": "Custom insert"
        },
        {
            "id": "partitions_write_custom_with_variable", 
            "title": "Custom insert with variables"
        }
    ], 
    "title": "Writing onto partitions"
}